pystopwatch/__init__.py
pystopwatch/__main__.py
pystopwatch/pystopwatch.py
pystopwatch-1.1.0.dist-info/LICENSE
pystopwatch-1.1.0.dist-info/METADATA
pystopwatch-1.1.0.dist-info/WHEEL
pystopwatch-1.1.0.dist-info/entry_points.txt
pystopwatch-1.1.0.dist-info/top_level.txt
pystopwatch-1.1.0.dist-info/RECORD
