Metadata-Version: 2.1
Name: pystopwatch
Version: 1.1.0
Summary: GUI StopWatch
Home-page: https://pystopwatch.readthedocs.io
Author: huwns
Author-email: huwnss2@gmail.com
License: BSD-3-Clause
Project-URL: Source, https://github.com/huwns/pystopwatch
Project-URL: Tracker, https://github.com/huwns/pystopwatch/issues
Keywords: stopwatch,time,presentation,gui
Platform: UNKNOWN
Classifier: Development Status :: 5 - Production/Stable
Classifier: Intended Audience :: End Users/Desktop
Classifier: License :: OSI Approved :: BSD License
Classifier: Operating System :: OS Independent
Classifier: Programming Language :: Python
License-File: LICENSE
